aim/__init__.py
aim/agents/__init__.py
aim/api/__init__.py
aim/api/client.py
aim/api/server.py
aim/cli/__init__.py
aim/cli/main.py
aim/config/default.json
aim/coordination/__init__.py
aim/coordination/collaborator.py
aim/coordination/router.py
aim/core/__init__.py
aim/core/agent.py
aim/core/context.py
aim/core/exceptions.py
aim/core/framework.py
aim/core/request.py
aim/knowledge/__init__.py
aim/knowledge/capsule.py
aim/knowledge/intent_graph.py
aim/knowledge/propagator.py
aim/resources/__init__.py
aim/resources/monitor.py
aim/resources/scaler.py
aim/utils/__init__.py
aim/utils/config.py
aim/utils/logger.py
aim_framework-1.0.0.dist-info/LICENSE_HEADER.txt
aim_framework-1.0.0.dist-info/METADATA
aim_framework-1.0.0.dist-info/WHEEL
aim_framework-1.0.0.dist-info/entry_points.txt
aim_framework-1.0.0.dist-info/top_level.txt
aim_framework-1.0.0.dist-info/RECORD
