Metadata-Version: 2.1
Name: aim-framework
Version: 1.0.0
Summary: Adaptive Intelligence Mesh - A distributed coordination system for AI deployment and interaction
Home-page: https://github.com/jasonviipers/aim-framework
Author: jasonviipers
Author-email: support@jasonviipers.com
Project-URL: Bug Reports, https://github.com/jasonviipers/aim-framework/issues
Project-URL: Source, https://github.com/jasonviipers/aim-framework
Project-URL: Documentation, https://aim-framework.readthedocs.io/
Keywords: ai artificial-intelligence distributed-systems mesh-network coordination agents
Classifier: Development Status :: 4 - Beta
Classifier: Intended Audience :: Developers
Classifier: Intended Audience :: Science/Research
Classifier: License :: OSI Approved :: MIT License
Classifier: Operating System :: OS Independent
Classifier: Programming Language :: Python :: 3
Classifier: Programming Language :: Python :: 3.8
Classifier: Programming Language :: Python :: 3.9
Classifier: Programming Language :: Python :: 3.10
Classifier: Programming Language :: Python :: 3.11
Classifier: Topic :: Scientific/Engineering :: Artificial Intelligence
Classifier: Topic :: Software Development :: Libraries :: Python Modules
Classifier: Topic :: System :: Distributed Computing
Requires-Python: >=3.8
License-File: LICENSE_HEADER.txt
Requires-Dist: asyncio-mqtt>=0.11.0
Requires-Dist: numpy>=1.21.0
Requires-Dist: pandas>=1.3.0
Requires-Dist: requests>=2.28.0
Requires-Dist: aiohttp>=3.8.0
Requires-Dist: websockets>=10.0
Requires-Dist: flask>=2.2.0
Requires-Dist: flask-cors>=4.0.0
Requires-Dist: gunicorn>=20.1.0
Requires-Dist: matplotlib>=3.5.0
Requires-Dist: plotly>=5.10.0
Requires-Dist: networkx>=2.8.0
Requires-Dist: scikit-learn>=1.1.0
Requires-Dist: pyyaml>=6.0
Requires-Dist: python-dotenv>=0.19.0
Requires-Dist: click>=8.0.0
Requires-Dist: pytest>=7.0.0
Requires-Dist: pytest-cov>=4.0.0
Requires-Dist: pytest-asyncio>=0.20.0
Requires-Dist: black>=22.0.0
Requires-Dist: flake8>=5.0.0
Requires-Dist: mypy>=0.991
Requires-Dist: pre-commit>=2.20.0
Requires-Dist: sphinx>=5.0.0
Requires-Dist: sphinx-rtd-theme>=1.0.0
Requires-Dist: myst-parser>=0.18.0
Requires-Dist: psutil>=5.9.0
Requires-Dist: memory-profiler>=0.60.0
Provides-Extra: api
Requires-Dist: flask>=2.2.0; extra == "api"
Requires-Dist: flask-cors>=4.0.0; extra == "api"
Requires-Dist: gunicorn>=20.1.0; extra == "api"
Provides-Extra: dev
Requires-Dist: pytest>=7.0.0; extra == "dev"
Requires-Dist: pytest-cov>=4.0.0; extra == "dev"
Requires-Dist: black>=22.0.0; extra == "dev"
Requires-Dist: flake8>=5.0.0; extra == "dev"
Requires-Dist: mypy>=0.991; extra == "dev"
Requires-Dist: pre-commit>=2.20.0; extra == "dev"
Provides-Extra: docs
Requires-Dist: sphinx>=5.0.0; extra == "docs"
Requires-Dist: sphinx-rtd-theme>=1.0.0; extra == "docs"
Requires-Dist: myst-parser>=0.18.0; extra == "docs"
Provides-Extra: visualization
Requires-Dist: matplotlib>=3.5.0; extra == "visualization"
Requires-Dist: plotly>=5.10.0; extra == "visualization"
Requires-Dist: networkx>=2.8.0; extra == "visualization"
